simplectf/__init__.py
simplectf/__main__.py
simplectf-0.0.1.dist-info/LICENSE.txt
simplectf-0.0.1.dist-info/METADATA
simplectf-0.0.1.dist-info/WHEEL
simplectf-0.0.1.dist-info/entry_points.txt
simplectf-0.0.1.dist-info/top_level.txt
simplectf-0.0.1.dist-info/RECORD
