Metadata-Version: 2.1
Name: simplectf
Version: 0.0.1
Summary: Setting up a python package
Home-page: UNKNOWN
Author: Albert Xu
Author-email: albert.t.xu@gmail.com
License: UNKNOWN
Platform: UNKNOWN
Classifier: Programming Language :: Python :: 3
Classifier: License :: OSI Approved :: MIT License
Classifier: Operating System :: OS Independent
Requires-Python: >=3.6
Requires-Dist: mrcfile
Requires-Dist: numpy
Requires-Dist: scipy
